langchain_g4f_chat/__init__.py
langchain_g4f_chat/core/__init__.py
langchain_g4f_chat/core/authentication.py
langchain_g4f_chat/core/providers.py
langchain_g4f_chat/core/providers_fixed.py
langchain_g4f_chat/core/utils.py
langchain_g4f_chat/g4f/__init__.py
langchain_g4f_chat/g4f/__main__.py
langchain_g4f_chat/g4f/config.py
langchain_g4f_chat/g4f/cookies.py
langchain_g4f_chat/g4f/debug.py
langchain_g4f_chat/g4f/errors.py
langchain_g4f_chat/g4f/files.py
langchain_g4f_chat/g4f/models.py
langchain_g4f_chat/g4f/typing.py
langchain_g4f_chat/g4f/version.py
langchain_g4f_chat/g4f/Provider/Aichat.py
langchain_g4f_chat/g4f/Provider/Ails.py
langchain_g4f_chat/g4f/Provider/ApiAirforce.py
langchain_g4f_chat/g4f/Provider/Blackbox.py
langchain_g4f_chat/g4f/Provider/Chatai.py
langchain_g4f_chat/g4f/Provider/Cloudflare.py
langchain_g4f_chat/g4f/Provider/Copilot.py
langchain_g4f_chat/g4f/Provider/DeepInfra.py
langchain_g4f_chat/g4f/Provider/EasyChat.py
langchain_g4f_chat/g4f/Provider/GLM.py
langchain_g4f_chat/g4f/Provider/Kimi.py
langchain_g4f_chat/g4f/Provider/Koala.py
langchain_g4f_chat/g4f/Provider/LambdaChat.py
langchain_g4f_chat/g4f/Provider/Mintlify.py
langchain_g4f_chat/g4f/Provider/OIVSCodeSer0501.py
langchain_g4f_chat/g4f/Provider/OIVSCodeSer2.py
langchain_g4f_chat/g4f/Provider/OperaAria.py
langchain_g4f_chat/g4f/Provider/PerplexityLabs.py
langchain_g4f_chat/g4f/Provider/Pizzagpt.py
langchain_g4f_chat/g4f/Provider/PollinationsAI.py
langchain_g4f_chat/g4f/Provider/PollinationsImage.py
langchain_g4f_chat/g4f/Provider/Qwen.py
langchain_g4f_chat/g4f/Provider/Startnest.py
langchain_g4f_chat/g4f/Provider/TeachAnything.py
langchain_g4f_chat/g4f/Provider/WeWordle.py
langchain_g4f_chat/g4f/Provider/Yqcloud.py
langchain_g4f_chat/g4f/Provider/__init__.py
langchain_g4f_chat/g4f/Provider/base_provider.py
langchain_g4f_chat/g4f/Provider/helper.py
langchain_g4f_chat/g4f/Provider/audio/EdgeTTS.py
langchain_g4f_chat/g4f/Provider/audio/MarkItDown.py
langchain_g4f_chat-0.1.7.dist-info/licenses/LICENCE
langchain_g4f_chat-0.1.7.dist-info/METADATA
langchain_g4f_chat-0.1.7.dist-info/WHEEL
langchain_g4f_chat-0.1.7.dist-info/top_level.txt
langchain_g4f_chat-0.1.7.dist-info/RECORD
