Metadata-Version: 2.4
Name: langchain-g4f-chat
Version: 0.1.7
Summary: LangChain integration for g4f
Keywords: langchain,gpt4free,g4f,openai,chatgpt,llm
Classifier: Programming Language :: Python :: 3
Classifier: Programming Language :: Python :: 3.8
Classifier: Programming Language :: Python :: 3.9
Classifier: Programming Language :: Python :: 3.10
Classifier: Programming Language :: Python :: 3.11
Classifier: Programming Language :: Python :: 3.12
Classifier: License :: OSI Approved :: MIT License
Classifier: Operating System :: OS Independent
Requires-Python: >=3.8
License-File: LICENCE
Requires-Dist: langchain-core>=0.1.0
Requires-Dist: pydantic>=2.0
Requires-Dist: typing-extensions
Requires-Dist: requests>=2.25.0
Requires-Dist: aiohttp>=3.8.0
Requires-Dist: curl-cffi>=0.6.2
Requires-Dist: pycryptodome
Requires-Dist: certifi
Requires-Dist: browser_cookie3
Requires-Dist: nest_asyncio
Requires-Dist: werkzeug
Requires-Dist: pillow
Requires-Dist: platformdirs
Requires-Dist: fastapi
Requires-Dist: uvicorn
Requires-Dist: flask
Requires-Dist: brotli
Requires-Dist: beautifulsoup4
Requires-Dist: setuptools
Requires-Dist: nodriver
Requires-Dist: python-multipart
Requires-Dist: a2wsgi
Requires-Dist: python-dotenv
Requires-Dist: ddgs
Dynamic: classifier
Dynamic: description
Dynamic: description-content-type
Dynamic: keywords
Dynamic: license-file
Dynamic: requires-dist
Dynamic: requires-python
Dynamic: summary
